{
  "source": "app_store",
  "reviews": [
    { "id": "as_001", "rating": 2, "text": "I had no idea what to do when I first opened the app. There is no tutorial and the onboarding just dumps you on a blank screen. Spent 20 minutes confused before giving up.", "date": "2025-12-01" },
    { "id": "as_002", "rating": 2, "text": "The setup process is really unclear. I could not figure out how to connect my first data source. Needs a proper walkthrough.", "date": "2025-12-03" },
    { "id": "as_003", "rating": 1, "text": "Getting started is a nightmare. The onboarding flow skips over basic steps and assumes you already know how everything works.", "date": "2025-12-05" },
    { "id": "as_004", "rating": 2, "text": "No onboarding guide at all. First time users are left completely in the dark. Please add a walkthrough or at least a tooltip tour.", "date": "2025-12-08" },
    { "id": "as_005", "rating": 3, "text": "App is powerful but the initial setup is confusing. Took me three tries to get my workspace configured correctly.", "date": "2025-12-10" },
    { "id": "as_006", "rating": 2, "text": "Why is there no onboarding checklist? Every other SaaS tool I use has one. Starting from scratch with zero guidance is frustrating.", "date": "2025-12-12" },
    { "id": "as_007", "rating": 1, "text": "App crashes every time I try to load a report with more than 500 rows. This has been happening for weeks and there is no fix.", "date": "2025-12-02" },
    { "id": "as_008", "rating": 1, "text": "Constant crashes on iOS 17. Opens fine but crashes after about 2 minutes of use. Unusable right now.", "date": "2025-12-04" },
    { "id": "as_009", "rating": 2, "text": "Performance is terrible. Loading the dashboard takes 15 seconds every time. The app needs serious optimization.", "date": "2025-12-06" },
    { "id": "as_010", "rating": 1, "text": "Crashes on startup since the last update. iPhone 14 Pro, iOS 17.2. Please fix this urgently.", "date": "2025-12-07" },
    { "id": "as_011", "rating": 2, "text": "The app is slow. Every action has a noticeable delay. Comparing this to competitors it feels years behind on performance.", "date": "2025-12-09" },
    { "id": "as_012", "rating": 1, "text": "I cannot use this app at all. It freezes on the data view screen. Have reinstalled three times. Same result.", "date": "2025-12-11" },
    { "id": "as_013", "rating": 2, "text": "Desperately need a bulk export feature. Right now I have to download reports one by one which takes forever for large datasets.", "date": "2025-12-13" },
    { "id": "as_014", "rating": 3, "text": "Good tool but missing bulk export. I manage 50 clients and downloading individual reports is not scalable.", "date": "2025-12-15" },
    { "id": "as_015", "rating": 2, "text": "Please add CSV export for all data at once. The current export only does single items and it is a huge time sink.", "date": "2025-12-17" },
    { "id": "as_016", "rating": 3, "text": "The navigation is confusing. I can never find the settings I am looking for. The menu structure does not match how I think about the product.", "date": "2025-12-14" },
    { "id": "as_017", "rating": 2, "text": "Hard to find anything in the sidebar. The information architecture needs a rethink. Important features are buried three levels deep.", "date": "2025-12-16" },
    { "id": "as_018", "rating": 2, "text": "Navigation is not intuitive at all. Took me 10 minutes to find where to manage integrations. Should be in the main menu.", "date": "2025-12-18" },
    { "id": "as_019", "rating": 5, "text": "Best analytics tool I have used. Clean interface, fast, and the insights are genuinely useful. Highly recommend.", "date": "2025-12-19" },
    { "id": "as_020", "rating": 5, "text": "Game changer for our product team. The way it surfaces patterns from our feedback is exactly what we needed.", "date": "2025-12-20" },
    { "id": "as_021", "rating": 1, "text": "Onboarding is completely broken. The welcome email link takes you to a 404 page. First impression ruined.", "date": "2025-12-21" },
    { "id": "as_022", "rating": 2, "text": "The app crashes whenever I switch between projects. Very reproducible. Happens every single time.", "date": "2025-12-22" },
    { "id": "as_023", "rating": 3, "text": "Decent app but needs bulk operations badly. Bulk archive, bulk export, bulk tag. Power users need these.", "date": "2025-12-23" },
    { "id": "as_024", "rating": 2, "text": "Setup took me a full day because there were no instructions. A simple getting started guide would save everyone so much time.", "date": "2025-12-24" },
    { "id": "as_025", "rating": 1, "text": "Memory leak on Android. The app gets progressively slower until the phone needs a restart. Known issue apparently.", "date": "2025-12-25" },
    { "id": "as_026", "rating": 4, "text": "Mostly great. The only thing I wish for is bulk export. Would make my weekly reporting workflow so much faster.", "date": "2025-12-26" },
    { "id": "as_027", "rating": 2, "text": "Cannot figure out the navigation. Where is the user management section? I have looked everywhere.", "date": "2025-12-27" },
    { "id": "as_028", "rating": 1, "text": "App is broken after the latest update. Black screen on launch. Please roll back or push a fix.", "date": "2025-12-28" },
    { "id": "as_029", "rating": 3, "text": "Useful product but the first-time experience is rough. I almost churned in the first week because I could not get started.", "date": "2025-12-29" },
    { "id": "as_030", "rating": 5, "text": "Excellent product. The team clearly listens to feedback. Keep up the great work.", "date": "2025-12-30" }
  ]
}
